{
  "type": "Program",
  "body": [
    {
      "type": "ImportDeclaration",
      "specifiers": [
        {
          "type": "ImportDefaultSpecifier",
          "local": {
            "type": "Identifier",
            "name": "nextchild",
            "range": [
              7,
              16
            ],
            "loc": {
              "start": {
                "line": 1,
                "column": 7
              },
              "end": {
                "line": 1,
                "column": 16
              }
            }
          },
          "range": [
            7,
            16
          ],
          "loc": {
            "start": {
              "line": 1,
              "column": 7
            },
            "end": {
              "line": 1,
              "column": 16
            }
          }
        }
      ],
      "source": {
        "type": "Literal",
        "value": "./nextchild",
        "raw": "'./nextchild'",
        "range": [
          22,
          35
        ],
        "loc": {
          "start": {
            "line": 1,
            "column": 22
          },
          "end": {
            "line": 1,
            "column": 35
          }
        }
      },
      "range": [
        0,
        37
      ],
      "loc": {
        "start": {
          "line": 1,
          "column": 0
        },
        "end": {
          "line": 1,
          "column": 37
        }
      },
      "trailingComments": [
        {
          "type": "Block",
          "value": "*\n * Sifts down a node.\n *\n * @param {function} compare the comparison function\n * @param {array} a the array where the heap is stored\n * @param {int} i is the root element\n * @param {int} j - 1 is the last leaf\n * @param {int} k is the target node\n ",
          "range": [
            39,
            293
          ],
          "loc": {
            "start": {
              "line": 3,
              "column": 0
            },
            "end": {
              "line": 11,
              "column": 3
            }
          }
        }
      ]
    },
    {
      "type": "ExportDefaultDeclaration",
      "declaration": {
        "type": "FunctionDeclaration",
        "id": {
          "type": "Identifier",
          "name": "siftdown",
          "range": [
            319,
            327
          ],
          "loc": {
            "start": {
              "line": 13,
              "column": 24
            },
            "end": {
              "line": 13,
              "column": 32
            }
          }
        },
        "params": [
          {
            "type": "Identifier",
            "name": "compare",
            "range": [
              330,
              337
            ],
            "loc": {
              "start": {
                "line": 13,
                "column": 35
              },
              "end": {
                "line": 13,
                "column": 42
              }
            }
          },
          {
            "type": "Identifier",
            "name": "a",
            "range": [
              339,
              340
            ],
            "loc": {
              "start": {
                "line": 13,
                "column": 44
              },
              "end": {
                "line": 13,
                "column": 45
              }
            }
          },
          {
            "type": "Identifier",
            "name": "i",
            "range": [
              342,
              343
            ],
            "loc": {
              "start": {
                "line": 13,
                "column": 47
              },
              "end": {
                "line": 13,
                "column": 48
              }
            }
          },
          {
            "type": "Identifier",
            "name": "j",
            "range": [
              345,
              346
            ],
            "loc": {
              "start": {
                "line": 13,
                "column": 50
              },
              "end": {
                "line": 13,
                "column": 51
              }
            }
          },
          {
            "type": "Identifier",
            "name": "k",
            "range": [
              348,
              349
            ],
            "loc": {
              "start": {
                "line": 13,
                "column": 53
              },
              "end": {
                "line": 13,
                "column": 54
              }
            }
          }
        ],
        "body": {
          "type": "BlockStatement",
          "body": [
            {
              "type": "VariableDeclaration",
              "declarations": [
                {
                  "type": "VariableDeclarator",
                  "id": {
                    "type": "Identifier",
                    "name": "current",
                    "range": [
                      360,
                      367
                    ],
                    "loc": {
                      "start": {
                        "line": 15,
                        "column": 5
                      },
                      "end": {
                        "line": 15,
                        "column": 12
                      }
                    }
                  },
                  "init": {
                    "type": "BinaryExpression",
                    "operator": "-",
                    "left": {
                      "type": "Identifier",
                      "name": "k",
                      "range": [
                        370,
                        371
                      ],
                      "loc": {
                        "start": {
                          "line": 15,
                          "column": 15
                        },
                        "end": {
                          "line": 15,
                          "column": 16
                        }
                      }
                    },
                    "right": {
                      "type": "Identifier",
                      "name": "i",
                      "range": [
                        374,
                        375
                      ],
                      "loc": {
                        "start": {
                          "line": 15,
                          "column": 19
                        },
                        "end": {
                          "line": 15,
                          "column": 20
                        }
                      }
                    },
                    "range": [
                      370,
                      375
                    ],
                    "loc": {
                      "start": {
                        "line": 15,
                        "column": 15
                      },
                      "end": {
                        "line": 15,
                        "column": 20
                      }
                    }
                  },
                  "range": [
                    360,
                    375
                  ],
                  "loc": {
                    "start": {
                      "line": 15,
                      "column": 5
                    },
                    "end": {
                      "line": 15,
                      "column": 20
                    }
                  }
                }
              ],
              "kind": "let",
              "range": [
                356,
                376
              ],
              "loc": {
                "start": {
                  "line": 15,
                  "column": 1
                },
                "end": {
                  "line": 15,
                  "column": 21
                }
              }
            },
            {
              "type": "WhileStatement",
              "test": {
                "type": "Literal",
                "value": true,
                "raw": "true",
                "range": [
                  387,
                  391
                ],
                "loc": {
                  "start": {
                    "line": 17,
                    "column": 9
                  },
                  "end": {
                    "line": 17,
                    "column": 13
                  }
                }
              },
              "body": {
                "type": "BlockStatement",
                "body": [
                  {
                    "type": "VariableDeclaration",
                    "declarations": [
                      {
                        "type": "VariableDeclarator",
                        "id": {
                          "type": "Identifier",
                          "name": "firstchild",
                          "range": [
                            471,
                            481
                          ],
                          "loc": {
                            "start": {
                              "line": 22,
                              "column": 8
                            },
                            "end": {
                              "line": 22,
                              "column": 18
                            }
                          }
                        },
                        "init": {
                          "type": "BinaryExpression",
                          "operator": "+",
                          "left": {
                            "type": "BinaryExpression",
                            "operator": "*",
                            "left": {
                              "type": "Literal",
                              "value": 2,
                              "raw": "2",
                              "range": [
                                484,
                                485
                              ],
                              "loc": {
                                "start": {
                                  "line": 22,
                                  "column": 21
                                },
                                "end": {
                                  "line": 22,
                                  "column": 22
                                }
                              }
                            },
                            "right": {
                              "type": "Identifier",
                              "name": "current",
                              "range": [
                                488,
                                495
                              ],
                              "loc": {
                                "start": {
                                  "line": 22,
                                  "column": 25
                                },
                                "end": {
                                  "line": 22,
                                  "column": 32
                                }
                              }
                            },
                            "range": [
                              484,
                              495
                            ],
                            "loc": {
                              "start": {
                                "line": 22,
                                "column": 21
                              },
                              "end": {
                                "line": 22,
                                "column": 32
                              }
                            }
                          },
                          "right": {
                            "type": "Literal",
                            "value": 1,
                            "raw": "1",
                            "range": [
                              498,
                              499
                            ],
                            "loc": {
                              "start": {
                                "line": 22,
                                "column": 35
                              },
                              "end": {
                                "line": 22,
                                "column": 36
                              }
                            }
                          },
                          "range": [
                            484,
                            499
                          ],
                          "loc": {
                            "start": {
                              "line": 22,
                              "column": 21
                            },
                            "end": {
                              "line": 22,
                              "column": 36
                            }
                          }
                        },
                        "range": [
                          471,
                          499
                        ],
                        "loc": {
                          "start": {
                            "line": 22,
                            "column": 8
                          },
                          "end": {
                            "line": 22,
                            "column": 36
                          }
                        }
                      }
                    ],
                    "kind": "const",
                    "range": [
                      465,
                      500
                    ],
                    "loc": {
                      "start": {
                        "line": 22,
                        "column": 2
                      },
                      "end": {
                        "line": 22,
                        "column": 37
                      }
                    },
                    "leadingComments": [
                      {
                        "type": "Line",
                        "value": " address of the first child in a zero-based",
                        "range": [
                          399,
                          444
                        ],
                        "loc": {
                          "start": {
                            "line": 19,
                            "column": 2
                          },
                          "end": {
                            "line": 19,
                            "column": 47
                          }
                        }
                      },
                      {
                        "type": "Line",
                        "value": " binary heap",
                        "range": [
                          447,
                          461
                        ],
                        "loc": {
                          "start": {
                            "line": 20,
                            "column": 2
                          },
                          "end": {
                            "line": 20,
                            "column": 16
                          }
                        }
                      }
                    ],
                    "trailingComments": [
                      {
                        "type": "Line",
                        "value": " if current node has no children",
                        "range": [
                          504,
                          538
                        ],
                        "loc": {
                          "start": {
                            "line": 24,
                            "column": 2
                          },
                          "end": {
                            "line": 24,
                            "column": 36
                          }
                        }
                      },
                      {
                        "type": "Line",
                        "value": " then we are done",
                        "range": [
                          541,
                          560
                        ],
                        "loc": {
                          "start": {
                            "line": 25,
                            "column": 2
                          },
                          "end": {
                            "line": 25,
                            "column": 21
                          }
                        }
                      }
                    ]
                  },
                  {
                    "type": "IfStatement",
                    "test": {
                      "type": "BinaryExpression",
                      "operator": ">=",
                      "left": {
                        "type": "Identifier",
                        "name": "firstchild",
                        "range": [
                          569,
                          579
                        ],
                        "loc": {
                          "start": {
                            "line": 27,
                            "column": 7
                          },
                          "end": {
                            "line": 27,
                            "column": 17
                          }
                        }
                      },
                      "right": {
                        "type": "BinaryExpression",
                        "operator": "-",
                        "left": {
                          "type": "Identifier",
                          "name": "j",
                          "range": [
                            583,
                            584
                          ],
                          "loc": {
                            "start": {
                              "line": 27,
                              "column": 21
                            },
                            "end": {
                              "line": 27,
                              "column": 22
                            }
                          }
                        },
                        "right": {
                          "type": "Identifier",
                          "name": "i",
                          "range": [
                            587,
                            588
                          ],
                          "loc": {
                            "start": {
                              "line": 27,
                              "column": 25
                            },
                            "end": {
                              "line": 27,
                              "column": 26
                            }
                          }
                        },
                        "range": [
                          583,
                          588
                        ],
                        "loc": {
                          "start": {
                            "line": 27,
                            "column": 21
                          },
                          "end": {
                            "line": 27,
                            "column": 26
                          }
                        }
                      },
                      "range": [
                        569,
                        588
                      ],
                      "loc": {
                        "start": {
                          "line": 27,
                          "column": 7
                        },
                        "end": {
                          "line": 27,
                          "column": 26
                        }
                      }
                    },
                    "consequent": {
                      "type": "BreakStatement",
                      "label": null,
                      "range": [
                        591,
                        598
                      ],
                      "loc": {
                        "start": {
                          "line": 27,
                          "column": 29
                        },
                        "end": {
                          "line": 27,
                          "column": 36
                        }
                      }
                    },
                    "alternate": null,
                    "range": [
                      564,
                      598
                    ],
                    "loc": {
                      "start": {
                        "line": 27,
                        "column": 2
                      },
                      "end": {
                        "line": 27,
                        "column": 36
                      }
                    },
                    "leadingComments": [
                      {
                        "type": "Line",
                        "value": " if current node has no children",
                        "range": [
                          504,
                          538
                        ],
                        "loc": {
                          "start": {
                            "line": 24,
                            "column": 2
                          },
                          "end": {
                            "line": 24,
                            "column": 36
                          }
                        }
                      },
                      {
                        "type": "Line",
                        "value": " then we are done",
                        "range": [
                          541,
                          560
                        ],
                        "loc": {
                          "start": {
                            "line": 25,
                            "column": 2
                          },
                          "end": {
                            "line": 25,
                            "column": 21
                          }
                        }
                      }
                    ],
                    "trailingComments": [
                      {
                        "type": "Line",
                        "value": " if current value is smaller than its smallest",
                        "range": [
                          602,
                          650
                        ],
                        "loc": {
                          "start": {
                            "line": 29,
                            "column": 2
                          },
                          "end": {
                            "line": 29,
                            "column": 50
                          }
                        }
                      },
                      {
                        "type": "Line",
                        "value": " child then we are done",
                        "range": [
                          653,
                          678
                        ],
                        "loc": {
                          "start": {
                            "line": 30,
                            "column": 2
                          },
                          "end": {
                            "line": 30,
                            "column": 27
                          }
                        }
                      }
                    ]
                  },
                  {
                    "type": "VariableDeclaration",
                    "declarations": [
                      {
                        "type": "VariableDeclarator",
                        "id": {
                          "type": "Identifier",
                          "name": "candidate",
                          "range": [
                            688,
                            697
                          ],
                          "loc": {
                            "start": {
                              "line": 32,
                              "column": 8
                            },
                            "end": {
                              "line": 32,
                              "column": 17
                            }
                          }
                        },
                        "init": {
                          "type": "CallExpression",
                          "callee": {
                            "type": "Identifier",
                            "name": "nextchild",
                            "range": [
                              700,
                              709
                            ],
                            "loc": {
                              "start": {
                                "line": 32,
                                "column": 20
                              },
                              "end": {
                                "line": 32,
                                "column": 29
                              }
                            }
                          },
                          "arguments": [
                            {
                              "type": "Identifier",
                              "name": "compare",
                              "range": [
                                711,
                                718
                              ],
                              "loc": {
                                "start": {
                                  "line": 32,
                                  "column": 31
                                },
                                "end": {
                                  "line": 32,
                                  "column": 38
                                }
                              }
                            },
                            {
                              "type": "Identifier",
                              "name": "a",
                              "range": [
                                720,
                                721
                              ],
                              "loc": {
                                "start": {
                                  "line": 32,
                                  "column": 40
                                },
                                "end": {
                                  "line": 32,
                                  "column": 41
                                }
                              }
                            },
                            {
                              "type": "BinaryExpression",
                              "operator": "+",
                              "left": {
                                "type": "Identifier",
                                "name": "i",
                                "range": [
                                  723,
                                  724
                                ],
                                "loc": {
                                  "start": {
                                    "line": 32,
                                    "column": 43
                                  },
                                  "end": {
                                    "line": 32,
                                    "column": 44
                                  }
                                }
                              },
                              "right": {
                                "type": "Identifier",
                                "name": "firstchild",
                                "range": [
                                  727,
                                  737
                                ],
                                "loc": {
                                  "start": {
                                    "line": 32,
                                    "column": 47
                                  },
                                  "end": {
                                    "line": 32,
                                    "column": 57
                                  }
                                }
                              },
                              "range": [
                                723,
                                737
                              ],
                              "loc": {
                                "start": {
                                  "line": 32,
                                  "column": 43
                                },
                                "end": {
                                  "line": 32,
                                  "column": 57
                                }
                              }
                            },
                            {
                              "type": "Identifier",
                              "name": "j",
                              "range": [
                                739,
                                740
                              ],
                              "loc": {
                                "start": {
                                  "line": 32,
                                  "column": 59
                                },
                                "end": {
                                  "line": 32,
                                  "column": 60
                                }
                              }
                            }
                          ],
                          "range": [
                            700,
                            742
                          ],
                          "loc": {
                            "start": {
                              "line": 32,
                              "column": 20
                            },
                            "end": {
                              "line": 32,
                              "column": 62
                            }
                          }
                        },
                        "range": [
                          688,
                          742
                        ],
                        "loc": {
                          "start": {
                            "line": 32,
                            "column": 8
                          },
                          "end": {
                            "line": 32,
                            "column": 62
                          }
                        }
                      }
                    ],
                    "kind": "const",
                    "range": [
                      682,
                      743
                    ],
                    "loc": {
                      "start": {
                        "line": 32,
                        "column": 2
                      },
                      "end": {
                        "line": 32,
                        "column": 63
                      }
                    },
                    "leadingComments": [
                      {
                        "type": "Line",
                        "value": " if current value is smaller than its smallest",
                        "range": [
                          602,
                          650
                        ],
                        "loc": {
                          "start": {
                            "line": 29,
                            "column": 2
                          },
                          "end": {
                            "line": 29,
                            "column": 50
                          }
                        }
                      },
                      {
                        "type": "Line",
                        "value": " child then we are done",
                        "range": [
                          653,
                          678
                        ],
                        "loc": {
                          "start": {
                            "line": 30,
                            "column": 2
                          },
                          "end": {
                            "line": 30,
                            "column": 27
                          }
                        }
                      }
                    ]
                  },
                  {
                    "type": "IfStatement",
                    "test": {
                      "type": "BinaryExpression",
                      "operator": "<=",
                      "left": {
                        "type": "CallExpression",
                        "callee": {
                          "type": "Identifier",
                          "name": "compare",
                          "range": [
                            752,
                            759
                          ],
                          "loc": {
                            "start": {
                              "line": 34,
                              "column": 7
                            },
                            "end": {
                              "line": 34,
                              "column": 14
                            }
                          }
                        },
                        "arguments": [
                          {
                            "type": "MemberExpression",
                            "computed": true,
                            "object": {
                              "type": "Identifier",
                              "name": "a",
                              "range": [
                                761,
                                762
                              ],
                              "loc": {
                                "start": {
                                  "line": 34,
                                  "column": 16
                                },
                                "end": {
                                  "line": 34,
                                  "column": 17
                                }
                              }
                            },
                            "property": {
                              "type": "BinaryExpression",
                              "operator": "+",
                              "left": {
                                "type": "Identifier",
                                "name": "i",
                                "range": [
                                  763,
                                  764
                                ],
                                "loc": {
                                  "start": {
                                    "line": 34,
                                    "column": 18
                                  },
                                  "end": {
                                    "line": 34,
                                    "column": 19
                                  }
                                }
                              },
                              "right": {
                                "type": "Identifier",
                                "name": "current",
                                "range": [
                                  767,
                                  774
                                ],
                                "loc": {
                                  "start": {
                                    "line": 34,
                                    "column": 22
                                  },
                                  "end": {
                                    "line": 34,
                                    "column": 29
                                  }
                                }
                              },
                              "range": [
                                763,
                                774
                              ],
                              "loc": {
                                "start": {
                                  "line": 34,
                                  "column": 18
                                },
                                "end": {
                                  "line": 34,
                                  "column": 29
                                }
                              }
                            },
                            "range": [
                              761,
                              775
                            ],
                            "loc": {
                              "start": {
                                "line": 34,
                                "column": 16
                              },
                              "end": {
                                "line": 34,
                                "column": 30
                              }
                            }
                          },
                          {
                            "type": "MemberExpression",
                            "computed": true,
                            "object": {
                              "type": "Identifier",
                              "name": "a",
                              "range": [
                                777,
                                778
                              ],
                              "loc": {
                                "start": {
                                  "line": 34,
                                  "column": 32
                                },
                                "end": {
                                  "line": 34,
                                  "column": 33
                                }
                              }
                            },
                            "property": {
                              "type": "Identifier",
                              "name": "candidate",
                              "range": [
                                779,
                                788
                              ],
                              "loc": {
                                "start": {
                                  "line": 34,
                                  "column": 34
                                },
                                "end": {
                                  "line": 34,
                                  "column": 43
                                }
                              }
                            },
                            "range": [
                              777,
                              789
                            ],
                            "loc": {
                              "start": {
                                "line": 34,
                                "column": 32
                              },
                              "end": {
                                "line": 34,
                                "column": 44
                              }
                            }
                          }
                        ],
                        "range": [
                          752,
                          791
                        ],
                        "loc": {
                          "start": {
                            "line": 34,
                            "column": 7
                          },
                          "end": {
                            "line": 34,
                            "column": 46
                          }
                        }
                      },
                      "right": {
                        "type": "Literal",
                        "value": 0,
                        "raw": "0",
                        "range": [
                          795,
                          796
                        ],
                        "loc": {
                          "start": {
                            "line": 34,
                            "column": 50
                          },
                          "end": {
                            "line": 34,
                            "column": 51
                          }
                        }
                      },
                      "range": [
                        752,
                        796
                      ],
                      "loc": {
                        "start": {
                          "line": 34,
                          "column": 7
                        },
                        "end": {
                          "line": 34,
                          "column": 51
                        }
                      }
                    },
                    "consequent": {
                      "type": "BreakStatement",
                      "label": null,
                      "range": [
                        799,
                        806
                      ],
                      "loc": {
                        "start": {
                          "line": 34,
                          "column": 54
                        },
                        "end": {
                          "line": 34,
                          "column": 61
                        }
                      }
                    },
                    "alternate": null,
                    "range": [
                      747,
                      806
                    ],
                    "loc": {
                      "start": {
                        "line": 34,
                        "column": 2
                      },
                      "end": {
                        "line": 34,
                        "column": 61
                      }
                    },
                    "trailingComments": [
                      {
                        "type": "Line",
                        "value": " otherwise",
                        "range": [
                          810,
                          822
                        ],
                        "loc": {
                          "start": {
                            "line": 36,
                            "column": 2
                          },
                          "end": {
                            "line": 36,
                            "column": 14
                          }
                        }
                      },
                      {
                        "type": "Line",
                        "value": " swap with smallest child",
                        "range": [
                          825,
                          852
                        ],
                        "loc": {
                          "start": {
                            "line": 37,
                            "column": 2
                          },
                          "end": {
                            "line": 37,
                            "column": 29
                          }
                        }
                      }
                    ]
                  },
                  {
                    "type": "VariableDeclaration",
                    "declarations": [
                      {
                        "type": "VariableDeclarator",
                        "id": {
                          "type": "Identifier",
                          "name": "tmp",
                          "range": [
                            862,
                            865
                          ],
                          "loc": {
                            "start": {
                              "line": 39,
                              "column": 8
                            },
                            "end": {
                              "line": 39,
                              "column": 11
                            }
                          }
                        },
                        "init": {
                          "type": "MemberExpression",
                          "computed": true,
                          "object": {
                            "type": "Identifier",
                            "name": "a",
                            "range": [
                              868,
                              869
                            ],
                            "loc": {
                              "start": {
                                "line": 39,
                                "column": 14
                              },
                              "end": {
                                "line": 39,
                                "column": 15
                              }
                            }
                          },
                          "property": {
                            "type": "BinaryExpression",
                            "operator": "+",
                            "left": {
                              "type": "Identifier",
                              "name": "i",
                              "range": [
                                870,
                                871
                              ],
                              "loc": {
                                "start": {
                                  "line": 39,
                                  "column": 16
                                },
                                "end": {
                                  "line": 39,
                                  "column": 17
                                }
                              }
                            },
                            "right": {
                              "type": "Identifier",
                              "name": "current",
                              "range": [
                                872,
                                879
                              ],
                              "loc": {
                                "start": {
                                  "line": 39,
                                  "column": 18
                                },
                                "end": {
                                  "line": 39,
                                  "column": 25
                                }
                              }
                            },
                            "range": [
                              870,
                              879
                            ],
                            "loc": {
                              "start": {
                                "line": 39,
                                "column": 16
                              },
                              "end": {
                                "line": 39,
                                "column": 25
                              }
                            }
                          },
                          "range": [
                            868,
                            880
                          ],
                          "loc": {
                            "start": {
                              "line": 39,
                              "column": 14
                            },
                            "end": {
                              "line": 39,
                              "column": 26
                            }
                          }
                        },
                        "range": [
                          862,
                          880
                        ],
                        "loc": {
                          "start": {
                            "line": 39,
                            "column": 8
                          },
                          "end": {
                            "line": 39,
                            "column": 26
                          }
                        }
                      }
                    ],
                    "kind": "const",
                    "range": [
                      856,
                      882
                    ],
                    "loc": {
                      "start": {
                        "line": 39,
                        "column": 2
                      },
                      "end": {
                        "line": 39,
                        "column": 28
                      }
                    },
                    "leadingComments": [
                      {
                        "type": "Line",
                        "value": " otherwise",
                        "range": [
                          810,
                          822
                        ],
                        "loc": {
                          "start": {
                            "line": 36,
                            "column": 2
                          },
                          "end": {
                            "line": 36,
                            "column": 14
                          }
                        }
                      },
                      {
                        "type": "Line",
                        "value": " swap with smallest child",
                        "range": [
                          825,
                          852
                        ],
                        "loc": {
                          "start": {
                            "line": 37,
                            "column": 2
                          },
                          "end": {
                            "line": 37,
                            "column": 29
                          }
                        }
                      }
                    ]
                  },
                  {
                    "type": "ExpressionStatement",
                    "expression": {
                      "type": "AssignmentExpression",
                      "operator": "=",
                      "left": {
                        "type": "MemberExpression",
                        "computed": true,
                        "object": {
                          "type": "Identifier",
                          "name": "a",
                          "range": [
                            885,
                            886
                          ],
                          "loc": {
                            "start": {
                              "line": 40,
                              "column": 2
                            },
                            "end": {
                              "line": 40,
                              "column": 3
                            }
                          }
                        },
                        "property": {
                          "type": "BinaryExpression",
                          "operator": "+",
                          "left": {
                            "type": "Identifier",
                            "name": "i",
                            "range": [
                              887,
                              888
                            ],
                            "loc": {
                              "start": {
                                "line": 40,
                                "column": 4
                              },
                              "end": {
                                "line": 40,
                                "column": 5
                              }
                            }
                          },
                          "right": {
                            "type": "Identifier",
                            "name": "current",
                            "range": [
                              889,
                              896
                            ],
                            "loc": {
                              "start": {
                                "line": 40,
                                "column": 6
                              },
                              "end": {
                                "line": 40,
                                "column": 13
                              }
                            }
                          },
                          "range": [
                            887,
                            896
                          ],
                          "loc": {
                            "start": {
                              "line": 40,
                              "column": 4
                            },
                            "end": {
                              "line": 40,
                              "column": 13
                            }
                          }
                        },
                        "range": [
                          885,
                          897
                        ],
                        "loc": {
                          "start": {
                            "line": 40,
                            "column": 2
                          },
                          "end": {
                            "line": 40,
                            "column": 14
                          }
                        }
                      },
                      "right": {
                        "type": "MemberExpression",
                        "computed": true,
                        "object": {
                          "type": "Identifier",
                          "name": "a",
                          "range": [
                            900,
                            901
                          ],
                          "loc": {
                            "start": {
                              "line": 40,
                              "column": 17
                            },
                            "end": {
                              "line": 40,
                              "column": 18
                            }
                          }
                        },
                        "property": {
                          "type": "Identifier",
                          "name": "candidate",
                          "range": [
                            902,
                            911
                          ],
                          "loc": {
                            "start": {
                              "line": 40,
                              "column": 19
                            },
                            "end": {
                              "line": 40,
                              "column": 28
                            }
                          }
                        },
                        "range": [
                          900,
                          912
                        ],
                        "loc": {
                          "start": {
                            "line": 40,
                            "column": 17
                          },
                          "end": {
                            "line": 40,
                            "column": 29
                          }
                        }
                      },
                      "range": [
                        885,
                        912
                      ],
                      "loc": {
                        "start": {
                          "line": 40,
                          "column": 2
                        },
                        "end": {
                          "line": 40,
                          "column": 29
                        }
                      }
                    },
                    "range": [
                      885,
                      914
                    ],
                    "loc": {
                      "start": {
                        "line": 40,
                        "column": 2
                      },
                      "end": {
                        "line": 40,
                        "column": 31
                      }
                    }
                  },
                  {
                    "type": "ExpressionStatement",
                    "expression": {
                      "type": "AssignmentExpression",
                      "operator": "=",
                      "left": {
                        "type": "MemberExpression",
                        "computed": true,
                        "object": {
                          "type": "Identifier",
                          "name": "a",
                          "range": [
                            917,
                            918
                          ],
                          "loc": {
                            "start": {
                              "line": 41,
                              "column": 2
                            },
                            "end": {
                              "line": 41,
                              "column": 3
                            }
                          }
                        },
                        "property": {
                          "type": "Identifier",
                          "name": "candidate",
                          "range": [
                            919,
                            928
                          ],
                          "loc": {
                            "start": {
                              "line": 41,
                              "column": 4
                            },
                            "end": {
                              "line": 41,
                              "column": 13
                            }
                          }
                        },
                        "range": [
                          917,
                          929
                        ],
                        "loc": {
                          "start": {
                            "line": 41,
                            "column": 2
                          },
                          "end": {
                            "line": 41,
                            "column": 14
                          }
                        }
                      },
                      "right": {
                        "type": "Identifier",
                        "name": "tmp",
                        "range": [
                          932,
                          935
                        ],
                        "loc": {
                          "start": {
                            "line": 41,
                            "column": 17
                          },
                          "end": {
                            "line": 41,
                            "column": 20
                          }
                        }
                      },
                      "range": [
                        917,
                        935
                      ],
                      "loc": {
                        "start": {
                          "line": 41,
                          "column": 2
                        },
                        "end": {
                          "line": 41,
                          "column": 20
                        }
                      }
                    },
                    "range": [
                      917,
                      937
                    ],
                    "loc": {
                      "start": {
                        "line": 41,
                        "column": 2
                      },
                      "end": {
                        "line": 41,
                        "column": 22
                      }
                    }
                  },
                  {
                    "type": "ExpressionStatement",
                    "expression": {
                      "type": "AssignmentExpression",
                      "operator": "=",
                      "left": {
                        "type": "Identifier",
                        "name": "current",
                        "range": [
                          941,
                          948
                        ],
                        "loc": {
                          "start": {
                            "line": 43,
                            "column": 2
                          },
                          "end": {
                            "line": 43,
                            "column": 9
                          }
                        }
                      },
                      "right": {
                        "type": "BinaryExpression",
                        "operator": "-",
                        "left": {
                          "type": "Identifier",
                          "name": "candidate",
                          "range": [
                            951,
                            960
                          ],
                          "loc": {
                            "start": {
                              "line": 43,
                              "column": 12
                            },
                            "end": {
                              "line": 43,
                              "column": 21
                            }
                          }
                        },
                        "right": {
                          "type": "Identifier",
                          "name": "i",
                          "range": [
                            963,
                            964
                          ],
                          "loc": {
                            "start": {
                              "line": 43,
                              "column": 24
                            },
                            "end": {
                              "line": 43,
                              "column": 25
                            }
                          }
                        },
                        "range": [
                          951,
                          964
                        ],
                        "loc": {
                          "start": {
                            "line": 43,
                            "column": 12
                          },
                          "end": {
                            "line": 43,
                            "column": 25
                          }
                        }
                      },
                      "range": [
                        941,
                        964
                      ],
                      "loc": {
                        "start": {
                          "line": 43,
                          "column": 2
                        },
                        "end": {
                          "line": 43,
                          "column": 25
                        }
                      }
                    },
                    "range": [
                      941,
                      965
                    ],
                    "loc": {
                      "start": {
                        "line": 43,
                        "column": 2
                      },
                      "end": {
                        "line": 43,
                        "column": 26
                      }
                    }
                  }
                ],
                "range": [
                  394,
                  969
                ],
                "loc": {
                  "start": {
                    "line": 17,
                    "column": 16
                  },
                  "end": {
                    "line": 45,
                    "column": 2
                  }
                }
              },
              "range": [
                379,
                969
              ],
              "loc": {
                "start": {
                  "line": 17,
                  "column": 1
                },
                "end": {
                  "line": 45,
                  "column": 2
                }
              }
            },
            {
              "type": "ReturnStatement",
              "argument": {
                "type": "BinaryExpression",
                "operator": "+",
                "left": {
                  "type": "Identifier",
                  "name": "i",
                  "range": [
                    979,
                    980
                  ],
                  "loc": {
                    "start": {
                      "line": 47,
                      "column": 8
                    },
                    "end": {
                      "line": 47,
                      "column": 9
                    }
                  }
                },
                "right": {
                  "type": "Identifier",
                  "name": "current",
                  "range": [
                    983,
                    990
                  ],
                  "loc": {
                    "start": {
                      "line": 47,
                      "column": 12
                    },
                    "end": {
                      "line": 47,
                      "column": 19
                    }
                  }
                },
                "range": [
                  979,
                  990
                ],
                "loc": {
                  "start": {
                    "line": 47,
                    "column": 8
                  },
                  "end": {
                    "line": 47,
                    "column": 19
                  }
                }
              },
              "range": [
                972,
                991
              ],
              "loc": {
                "start": {
                  "line": 47,
                  "column": 1
                },
                "end": {
                  "line": 47,
                  "column": 20
                }
              }
            }
          ],
          "range": [
            352,
            994
          ],
          "loc": {
            "start": {
              "line": 13,
              "column": 57
            },
            "end": {
              "line": 49,
              "column": 1
            }
          }
        },
        "generator": false,
        "expression": false,
        "range": [
          310,
          994
        ],
        "loc": {
          "start": {
            "line": 13,
            "column": 15
          },
          "end": {
            "line": 49,
            "column": 1
          }
        },
        "leadingComments": [
          {
            "type": "Block",
            "value": "*\n * Sifts down a node.\n *\n * @param {function} compare the comparison function\n * @param {array} a the array where the heap is stored\n * @param {int} i is the root element\n * @param {int} j - 1 is the last leaf\n * @param {int} k is the target node\n ",
            "range": [
              39,
              293
            ],
            "loc": {
              "start": {
                "line": 3,
                "column": 0
              },
              "end": {
                "line": 11,
                "column": 3
              }
            }
          }
        ],
        "trailingComments": []
      },
      "range": [
        295,
        994
      ],
      "loc": {
        "start": {
          "line": 13,
          "column": 0
        },
        "end": {
          "line": 49,
          "column": 1
        }
      },
      "leadingComments": [
        {
          "type": "Block",
          "value": "*\n * Sifts down a node.\n *\n * @param {function} compare the comparison function\n * @param {array} a the array where the heap is stored\n * @param {int} i is the root element\n * @param {int} j - 1 is the last leaf\n * @param {int} k is the target node\n ",
          "range": [
            39,
            293
          ],
          "loc": {
            "start": {
              "line": 3,
              "column": 0
            },
            "end": {
              "line": 11,
              "column": 3
            }
          }
        }
      ]
    }
  ],
  "sourceType": "module",
  "range": [
    0,
    994
  ],
  "loc": {
    "start": {
      "line": 1,
      "column": 0
    },
    "end": {
      "line": 49,
      "column": 1
    }
  },
  "comments": [
    {
      "type": "Block",
      "value": "*\n * Sifts down a node.\n *\n * @param {function} compare the comparison function\n * @param {array} a the array where the heap is stored\n * @param {int} i is the root element\n * @param {int} j - 1 is the last leaf\n * @param {int} k is the target node\n ",
      "range": [
        39,
        293
      ],
      "loc": {
        "start": {
          "line": 3,
          "column": 0
        },
        "end": {
          "line": 11,
          "column": 3
        }
      }
    },
    {
      "type": "Line",
      "value": " address of the first child in a zero-based",
      "range": [
        399,
        444
      ],
      "loc": {
        "start": {
          "line": 19,
          "column": 2
        },
        "end": {
          "line": 19,
          "column": 47
        }
      }
    },
    {
      "type": "Line",
      "value": " binary heap",
      "range": [
        447,
        461
      ],
      "loc": {
        "start": {
          "line": 20,
          "column": 2
        },
        "end": {
          "line": 20,
          "column": 16
        }
      }
    },
    {
      "type": "Line",
      "value": " if current node has no children",
      "range": [
        504,
        538
      ],
      "loc": {
        "start": {
          "line": 24,
          "column": 2
        },
        "end": {
          "line": 24,
          "column": 36
        }
      }
    },
    {
      "type": "Line",
      "value": " then we are done",
      "range": [
        541,
        560
      ],
      "loc": {
        "start": {
          "line": 25,
          "column": 2
        },
        "end": {
          "line": 25,
          "column": 21
        }
      }
    },
    {
      "type": "Line",
      "value": " if current value is smaller than its smallest",
      "range": [
        602,
        650
      ],
      "loc": {
        "start": {
          "line": 29,
          "column": 2
        },
        "end": {
          "line": 29,
          "column": 50
        }
      }
    },
    {
      "type": "Line",
      "value": " child then we are done",
      "range": [
        653,
        678
      ],
      "loc": {
        "start": {
          "line": 30,
          "column": 2
        },
        "end": {
          "line": 30,
          "column": 27
        }
      }
    },
    {
      "type": "Line",
      "value": " otherwise",
      "range": [
        810,
        822
      ],
      "loc": {
        "start": {
          "line": 36,
          "column": 2
        },
        "end": {
          "line": 36,
          "column": 14
        }
      }
    },
    {
      "type": "Line",
      "value": " swap with smallest child",
      "range": [
        825,
        852
      ],
      "loc": {
        "start": {
          "line": 37,
          "column": 2
        },
        "end": {
          "line": 37,
          "column": 29
        }
      }
    }
  ]
}